setup.py
matvey_ma/__init__.py
matvey_ma/one.py
matvey_ma/two.py
matvey_ma.egg-info/PKG-INFO
matvey_ma.egg-info/SOURCES.txt
matvey_ma.egg-info/dependency_links.txt
matvey_ma.egg-info/top_level.txt