Metadata-Version: 2.1
Name: matvey_ma
Version: 0.0.1
Summary: My Package
Author: Your Name
Author-email: your@domain.com
